time_agnostic_library/__init__.py
time_agnostic_library/agnostic_entity.py
time_agnostic_library/agnostic_query.py
time_agnostic_library/prov_entity.py
time_agnostic_library/sparql.py
time_agnostic_library/support.py
time_agnostic_library-5.0.7.dist-info/METADATA
time_agnostic_library-5.0.7.dist-info/WHEEL
time_agnostic_library-5.0.7.dist-info/entry_points.txt
time_agnostic_library-5.0.7.dist-info/licenses/LICENSE.md
time_agnostic_library-5.0.7.dist-info/RECORD
