Metadata-Version: 2.4
Name: time-agnostic-library
Version: 5.0.7
Summary: time-agnostic-library is a Python ≥3.7 library that allows performing time-travel queries on RDF datasets compliant with the OCDM v2.0.1 provenance specification.
License: ISC
License-File: LICENSE.md
Keywords: rdf,provenance,opencitations,change-tracking,time-traversal query
Author: Arcangelo Massari
Author-email: arcangelo.massari@unibo.it
Requires-Python: >=3.9,<3.14
Classifier: Development Status :: 4 - Beta
Classifier: Intended Audience :: Science/Research
Classifier: License :: OSI Approved
Classifier: License :: OSI Approved :: ISC License (ISCL)
Classifier: Natural Language :: English
Classifier: Operating System :: OS Independent
Classifier: Programming Language :: Python :: 3
Classifier: Programming Language :: Python :: 3.9
Classifier: Programming Language :: Python :: 3.10
Classifier: Programming Language :: Python :: 3.11
Classifier: Programming Language :: Python :: 3.12
Classifier: Programming Language :: Python :: 3.13
Classifier: Topic :: Software Development :: Libraries :: Python Modules
Requires-Dist: SPARQLWrapper (==2.0.0)
Requires-Dist: python_dateutil (>=2.8.2,<3.0.0)
Requires-Dist: rdflib (>=7.1.4,<8.0.0)
Requires-Dist: tqdm (>=4.62.3,<5.0.0)
Project-URL: Documentation, https://time-agnostic-library.readthedocs.io
Project-URL: Homepage, https://github.com/opencitations/time-agnostic-library
Project-URL: Repository, https://github.com/opencitations/time-agnostic-library
